pcluster_cli/__init__.py
pcluster_cli/main.py
pcluster_cli/node-startup.sh
pcluster_cli/pcluster.yaml
pcluster_cli-0.1.2.dist-info/WHEEL
pcluster_cli-0.1.2.dist-info/entry_points.txt
pcluster_cli-0.1.2.dist-info/METADATA
pcluster_cli-0.1.2.dist-info/RECORD
