Metadata-Version: 2.1
Name: pcluster-cli
Version: 0.1.2
Summary: CLI for easy AWS parallel cluster management
Author: rsingh
Author-email: rsingh@altoslabs.com
Requires-Python: >=3.10,<4.0
Classifier: Programming Language :: Python :: 3
Classifier: Programming Language :: Python :: 3.10
Classifier: Programming Language :: Python :: 3.11
Requires-Dist: aws-parallelcluster (>=3.4.1,<4.0.0)
Requires-Dist: jinja2 (>=3.1.2,<4.0.0)
Requires-Dist: sentry-sdk (>=1.14.0,<2.0.0)
Requires-Dist: tabulate (==0.8.10)
